{
    "pkg": "com.gxicon.gxdiy_test",
    "app": "gxdiy_test",
    "vname": "0.0.0.1",
    "vcode": "12345678",
    "author": "[@weng](copy:@weng)",
    "color_primary": "#f44336",
    "color_primary_dark": "#d80f00",
    "color_accent": "#ff5252",
    "icons": [
        [
            "474",
            "com.Linnaeusiconpack.zsj",
            "//gxicon.b0.upaiyun.com/2017/08/29/18/20170829060828_b8d39bc973001fe304b50c55704072f0.png"
        ],
        [
            "471",
            "com.eg.android.AlipayGphone",
            "//gxicon.b0.upaiyun.com/2017/08/29/18/20170829060012_9a32ca29f0b57b6639d4af667fa753e4.png"
        ],
        [
            "467",
            "com.baidu.netdisk",
            "//gxicon.b0.upaiyun.com/2017/08/29/17/20170829054948_96768d7ba8643fa1d0cde41eea19c907.png"
        ],
        [
            "468",
            "com.tencent.mtt",
            "//gxicon.b0.upaiyun.com/2017/08/29/17/20170829055002_b16f93e364b9d088588064cee2cbc6bf.png"
        ],
        [
            "453",
            "com.youku.phone",
            "//gxicon.b0.upaiyun.com/2017/08/29/17/20170829053334_cf8002278f13e6d909218c083b1b3dbd.png"
        ]
    ]
}